{
  "AcidSlime_M": {
    "NORMAL_TACKLE": "Плевок"
  },
  "AcidSlime_S": {
    "TACKLE": "Плевок"
  },
  "FungiBeast": {
    "BITE": "Укус"
  },
  "GremlinNob": {
    "BULL_RUSH": "Рывок рогами",
    "SKULL_BASH": "Раздробить череп",
    "UNIQUE_1": "получает +{num} к Силе за каждую сыгранную карту Навыка"
  },
  "JawWorm": {
    "CHOMP": "Погрызть"
  },
  "Looter": {
    "SMOKE_BOMB": "Дымовая бомба",
    "ESCAPE": "Побег",
    "UNIQUE_1": "сбегает с боя"
  },
  "LouseDefensive": {
    "BITE": "Укус"
  },
  "LouseNormal": {
    "BITE": "Укус"
  },
  "Sentry": {
    "BOLT": "Разряд",
    "BEAM": "Луч"
  },
  "SpikeSlime_M": {
    "FLAME_TACKLE": "Плевок огнем"
  }
}